[ {
  "doctor" : {
    "id" : 13,
    "name" : "Brinta",
    "contact" : "0987654321",
    "email" : "brinta@gmail.com",
    "address" : "brinta villa",
    "dob" : [ 2024, 12, 15 ],
    "age" : 22,
    "department" : "Cardiology",
    "specialization" : "Electropsysiology",
    "qualification" : "MD",
    "startTime" : "05:13",
    "endTime" : "07:13",
    "availableFromDay" : "Monday",
    "availableToDay" : "Thursday",
    "consultationFee" : 300.0
  },
  "date" : "17 December 2024",
  "availableSlots" : [ "09:00 AM", "09:30 AM", "09:45 AM", "10:00 AM", "10:15 AM", "10:30 AM", "10:45 AM", "11:00 AM", "11:15 AM", "11:30 AM", "11:45 AM", "12:00 PM", "12:15 PM", "12:30 PM", "12:45 PM", "01:00 PM", "01:15 PM", "01:30 PM", "01:45 PM", "02:00 PM", "02:15 PM", "02:30 PM", "02:45 PM", "03:00 PM", "03:15 PM", "03:30 PM", "03:45 PM", "04:00 PM", "04:15 PM", "04:30 PM", "04:45 PM", "05:00 PM", "05:15 PM", "05:30 PM", "05:45 PM" ]
} ]